airflow_providers_impala_to_pg/ImpalaToPostgresSyncOperator.py
airflow_providers_impala_to_pg/__init__.py
airflow_providers_impala_to_pg-0.1.8.dist-info/METADATA
airflow_providers_impala_to_pg-0.1.8.dist-info/WHEEL
airflow_providers_impala_to_pg-0.1.8.dist-info/top_level.txt
airflow_providers_impala_to_pg-0.1.8.dist-info/RECORD
